west_ishara/__init__.py
west_ishara-0.0.0.dist-info/LICENSE.txt
west_ishara-0.0.0.dist-info/METADATA
west_ishara-0.0.0.dist-info/WHEEL
west_ishara-0.0.0.dist-info/top_level.txt
west_ishara-0.0.0.dist-info/RECORD
